ahfs-2025.8.dist-info/licenses/COPYING
ahfs-2025.8.dist-info/licenses/COPYING.LESSER
ahfs_class/ahfs.py
evaluators/e_AgiLM.py
evaluators/helpers/eval.py
evaluators/src/LM/lm.py
evaluators/src/LM/lm_torch.py
feasel/f_FCBF.py
feasel/f_FCBFiP.py
feasel/f_FFSA.py
feasel/f_LCFS.py
feasel/f_MMIFS.py
feasel/f_NMIFS.py
feasel/f_ORIG.py
feasel/f_mFCBF.py
feasel/f_mRMR.py
feasel/helpers/feasel_frame.py
utils/example.py
utils/logs.py
utils/metrics.py
utils/nn_test.py
utils/postprocessing.py
utils/preprocessing.py
utils/presets.py
utils/helpers/loader.py
ahfs-2025.8.dist-info/METADATA
ahfs-2025.8.dist-info/WHEEL
ahfs-2025.8.dist-info/top_level.txt
ahfs-2025.8.dist-info/RECORD
