Metadata-Version: 2.4
Name: ahfs
Version: 2025.8
Summary: Python implementation of the Adaptive, Hybrid Feature Selection algorithm.
Author-email: Bence Gercuj <bencegercuj@gmail.com>, Anh Tuan Hoang <hoang.anh.tuan@sztaki.hun-ren.hu>, Zsolt Janos Viharos <viharos.zsolt@sztaki.hun-ren.hu>
License-Expression: LGPL-3.0-or-later
Project-URL: Documentation, https://ahfs.readthedocs.io/en/latest/
Project-URL: Repository, https://github.com/BenGercuj/ahfs
Keywords: ahfs,feature selection,SZTAKI
Classifier: Development Status :: 6 - Mature
Classifier: Intended Audience :: Developers
Classifier: Intended Audience :: Science/Research
Classifier: Programming Language :: Python :: 3.11
Classifier: Topic :: Scientific/Engineering :: Artificial Intelligence
Requires-Python: >=3.11
License-File: COPYING
License-File: COPYING.LESSER
Requires-Dist: pandas>=2.2.3
Requires-Dist: matplotlib>=3.10.0
Requires-Dist: pymatreader>=1.0.0
Requires-Dist: seaborn>=0.13.2
Requires-Dist: pyitlib>=0.3.1
Requires-Dist: numpy>=1.26.4
Requires-Dist: scikit-learn>=1.6.1
Requires-Dist: torch>=2.7.1
Dynamic: license-file
